tfclass_predict/__init__.py
tfclass_predict/cli_interface.py
tfclass_predict/constants.py
tfclass_predict/io_interface.py
tfclass_predict/prediction_manager.py
tfclass_predict/predictor.py
tfclass_predict/sequence_processor.py
tfclass_predict-0.1.0.dist-info/LICENSE
tfclass_predict-0.1.0.dist-info/METADATA
tfclass_predict-0.1.0.dist-info/WHEEL
tfclass_predict-0.1.0.dist-info/entry_points.txt
tfclass_predict-0.1.0.dist-info/top_level.txt
tfclass_predict-0.1.0.dist-info/RECORD
