Metadata-Version: 2.1
Name: tfclass_predict
Version: 0.1.0
Summary: tfclass_predict allows to estimate transcription factor bindingsites in the TFClass hierarchy.
Author-email: Hazal Timucin <hazal.timucin@med.uni-goettingen.de>, Christian Ickes <christian.ickes@med.uni-goettingen.de>
Project-URL: Homepage, https://gitlab.gwdg.de/hti/tfclass_dnabert
Project-URL: Issues, https://gitlab.gwdg.de/hti/tfclass_dnabert/-/issues
Classifier: Programming Language :: Python :: 3
Classifier: Programming Language :: Python :: 3.9
Classifier: Programming Language :: Python :: 3.10
Classifier: Programming Language :: Python :: 3.11
Classifier: Development Status :: 4 - Beta
Classifier: License :: OSI Approved :: GNU Lesser General Public License v3 (LGPLv3)
Classifier: Operating System :: Unix
Requires-Python: >=3.9
License-File: LICENSE
Requires-Dist: transformers>=4.20.0
Requires-Dist: tensorflow>=2.17.0
Requires-Dist: pysam
Requires-Dist: tf-keras>=2.17.0
Requires-Dist: numpy
Requires-Dist: pandas
